zprint.py
zprint-0.0.11.dist-info/METADATA
zprint-0.0.11.dist-info/RECORD
zprint-0.0.11.dist-info/WHEEL
zprint-0.0.11.dist-info/top_level.txt
