Metadata-Version: 2.1
Name: zprint
Version: 0.0.11
Summary: print out the time and function trees
Home-page: http://www.zhaomingming.cn
Author: zhaomingming
Author-email: 13271929138@163.com
License: MIT
Platform: any
